featuringdata/__init__.py
featuringdata/featureSelector/__init__.py
featuringdata/featureSelector/_create_pdf_report.py
featuringdata/featureSelector/_features_select.py
featuringdata/featureSelector/_generate_plots.py
featuringdata/featureSelector/_recursive_fit.py
featuringdata/featuresEDA/__init__.py
featuringdata/featuresEDA/_correlation.py
featuringdata/featuresEDA/_create_pdf_report.py
featuringdata/featuresEDA/_features_eda.py
featuringdata/featuresEDA/_generate_plots.py
featuringdata/featuresEDA/_initial_eda_functions.py
featuring_data-0.3.0.dist-info/LICENSE
featuring_data-0.3.0.dist-info/METADATA
featuring_data-0.3.0.dist-info/WHEEL
featuring_data-0.3.0.dist-info/top_level.txt
featuring_data-0.3.0.dist-info/RECORD
