Metadata-Version: 2.1
Name: featuring-data
Version: 0.3.0
Summary: This package is designed to help anyone with a new dataset get started with EDA quickly.
Author-email: "Daniel M. Capellupo" <daniel@dmcdatascience.com>
Project-URL: Homepage, https://github.com/dancapellupo/featuring-data
Project-URL: Issues, https://github.com/dancapellupo/featuring-data/issues
Classifier: Programming Language :: Python :: 3
Classifier: License :: OSI Approved :: MIT License
Classifier: Operating System :: OS Independent
Requires-Python: >=3.8
License-File: LICENSE
Requires-Dist: numpy >=1.22.0
Requires-Dist: pandas >=1.4.0
Requires-Dist: matplotlib >=3.6.0
Requires-Dist: seaborn >=0.13.0
Requires-Dist: scipy >=1.7.3
Requires-Dist: scikit-learn >=1.0.2
Requires-Dist: xgboost >=1.6.0
Requires-Dist: fpdf >=1.7.2
Requires-Dist: tqdm >=4.40.0
